mcpify/__init__.py
mcpify/__main__.py
mcpify/backend.py
mcpify/cli.py
mcpify/detect.py
mcpify/validate.py
mcpify/wrapper.py
mcpify-0.1.4.dist-info/METADATA
mcpify-0.1.4.dist-info/WHEEL
mcpify-0.1.4.dist-info/entry_points.txt
mcpify-0.1.4.dist-info/licenses/LICENSE
mcpify-0.1.4.dist-info/RECORD
