Metadata-Version: 2.4
Name: mcpify
Version: 0.1.4
Summary: Turn existing projects into MCP servers
Project-URL: Homepage, https://github.com/mugglejinx/mcpify
Project-URL: Documentation, https://github.com/muggleji/mcpify#readme
Project-URL: Repository, https://github.com/muggleji/mcpify.git
Project-URL: Bug Tracker, https://github.com/muggleji/mcpify/issues
Project-URL: Changelog, https://github.com/muggleji/mcpify/blob/main/CHANGELOG.md
Author-email: Xiaotian Jin <jin.xiaotian.kim@gmail.com>
Maintainer-email: Xiaotian Jin <jin.xiaotian.kim@gmail.com>
License: MIT
License-File: LICENSE
Keywords: ai,api,automation,mcp,model-context-protocol,server
Classifier: Development Status :: 4 - Beta
Classifier: Intended Audience :: Developers
Classifier: License :: OSI Approved :: MIT License
Classifier: Operating System :: OS Independent
Classifier: Programming Language :: Python :: 3
Classifier: Programming Language :: Python :: 3.10
Classifier: Programming Language :: Python :: 3.11
Classifier: Programming Language :: Python :: 3.12
Classifier: Topic :: Internet :: WWW/HTTP :: HTTP Servers
Classifier: Topic :: Software Development :: Libraries :: Python Modules
Classifier: Topic :: System :: Systems Administration
Classifier: Topic :: Utilities
Requires-Python: >=3.10
Requires-Dist: aiohttp>=3.12.2
Requires-Dist: mcp[cli]>=1.9.1
Requires-Dist: openai>=1.0.0
Provides-Extra: all
Requires-Dist: bandit[toml]>=1.7.0; extra == 'all'
Requires-Dist: fastapi>=0.104.1; extra == 'all'
Requires-Dist: flask>=2.3.0; extra == 'all'
Requires-Dist: mypy>=1.5.0; extra == 'all'
Requires-Dist: pre-commit>=3.0.0; extra == 'all'
Requires-Dist: pydantic>=2.5.0; extra == 'all'
Requires-Dist: pytest-asyncio>=0.21.0; extra == 'all'
Requires-Dist: pytest-cov>=4.1.0; extra == 'all'
Requires-Dist: pytest>=7.4.0; extra == 'all'
Requires-Dist: python-dateutil>=2.8.2; extra == 'all'
Requires-Dist: requests>=2.31.0; extra == 'all'
Requires-Dist: ruff>=0.1.0; extra == 'all'
Requires-Dist: safety>=2.3.0; extra == 'all'
Requires-Dist: uvicorn[standard]>=0.24.0; extra == 'all'
Provides-Extra: dev
Requires-Dist: bandit[toml]>=1.7.0; extra == 'dev'
Requires-Dist: mypy>=1.5.0; extra == 'dev'
Requires-Dist: pre-commit>=3.0.0; extra == 'dev'
Requires-Dist: pytest-asyncio>=0.21.0; extra == 'dev'
Requires-Dist: pytest-cov>=4.1.0; extra == 'dev'
Requires-Dist: pytest>=7.4.0; extra == 'dev'
Requires-Dist: ruff>=0.1.0; extra == 'dev'
Requires-Dist: safety>=2.3.0; extra == 'dev'
Provides-Extra: examples
Requires-Dist: fastapi>=0.104.1; extra == 'examples'
Requires-Dist: flask>=2.3.0; extra == 'examples'
Requires-Dist: pydantic>=2.5.0; extra == 'examples'
Requires-Dist: python-dateutil>=2.8.2; extra == 'examples'
Requires-Dist: requests>=2.31.0; extra == 'examples'
Requires-Dist: uvicorn[standard]>=0.24.0; extra == 'examples'
